pymetservice/__init__.py
pymetservice-0.0.1.dist-info/LICENSE
pymetservice-0.0.1.dist-info/METADATA
pymetservice-0.0.1.dist-info/WHEEL
pymetservice-0.0.1.dist-info/top_level.txt
pymetservice-0.0.1.dist-info/RECORD
