Metadata-Version: 2.1
Name: pymetservice
Version: 0.0.1
Summary: MetService Python API Wrapper
Home-page: https://github.com/ZephireNZ/PyMetService
Author: ZephireNZ
Author-email: brynley+pypi@zephire.nz
License: UNKNOWN
Platform: UNKNOWN
Classifier: Programming Language :: Python :: 3
Classifier: License :: OSI Approved :: MIT License
Classifier: Operating System :: OS Independent
Requires-Python: >=3.6
